[
  {
    "question": "What happens the exact moment Python encounters the 'break' keyword inside a loop?",
    "options": {
      "A": "The loop takes a temporary pause and then continues",
      "B": "The loop stops immediately and the computer jumps to the code below the loop",
      "C": "The computer restarts the entire program from line 1",
      "D": "The loop starts running backwards"
    },
    "answer": "B"
  },
  {
    "question": "Look at this code snippet:\n\nfor number in range(10):\n    print(number)\n    if number == 3:\n        break\n\nWhat is the very last number that will be printed on the screen?",
    "options": {
      "A": "10",
      "B": "9",
      "C": "3",
      "D": "4"
    },
    "answer": "C"
  },
  {
    "question": "Why do programmers call the 'break' statement an \"escape hatch\" or \"secret escape key\"?",
    "options": {
      "A": "Because it deletes code that has errors in it",
      "B": "Because it allows a loop to finish even if the computer turns off",
      "C": "Because it lets you exit out of an infinite loop when a specific event happens",
      "D": "Because it hides your code from other people"
    },
    "answer": "C"
  },
  {
    "question": "Look at this loop searching through a backpack:\n\nitems = [\"Pencil\", \"Apple\", \"Key\", \"Book\"]\nfor item in items:\n    print(item)\n    if item == \"Key\":\n        break\n\nWhich item will NOT be printed because the loop broke early?",
    "options": {
      "A": "Pencil",
      "B": "Apple",
      "C": "Key",
      "D": "Book"
    },
    "answer": "D"
  },
  {
    "question": "Inside a 'while True:' loop, what typically triggers a 'break' statement to run?",
    "options": {
      "A": "An 'if' statement checking if a certain condition has become true",
      "B": "A mathematical equation adding two large numbers",
      "C": "A 'print' statement showing a message to the user",
      "D": "The loop simply running out of steps automatically"
    },
    "answer": "A"
  }
]